anns/__init__.py
anns-0.0.1.dist-info/LICENSE
anns-0.0.1.dist-info/METADATA
anns-0.0.1.dist-info/WHEEL
anns-0.0.1.dist-info/RECORD
